optionprice/__init__.py
optionprice/option.py
option_price-0.2.0.dist-info/LICENSE
option_price-0.2.0.dist-info/METADATA
option_price-0.2.0.dist-info/WHEEL
option_price-0.2.0.dist-info/top_level.txt
option_price-0.2.0.dist-info/RECORD
