Metadata-Version: 2.1
Name: option-price
Version: 0.2.0
Summary: Awesome but light option price calculator in Python
Home-page: https://qsctech-sange.github.io/option-price
Author: QSCTech-Sange
Author-email: 3160105521@zju.edu.cn
License: UNKNOWN
Platform: UNKNOWN
Classifier: Programming Language :: Python :: 3
Classifier: License :: OSI Approved :: MIT License
Classifier: Operating System :: OS Independent
Requires-Python: >=3.6
Requires-Dist: numpy
Requires-Dist: scipy
